schistoscope/AEF_program.py
schistoscope/Camera_test.py
schistoscope/GUI_test.py
schistoscope/TFT_test.py
schistoscope/__init__.py
schistoscope/led_pwm_test.py
schistoscope/main_program.py
schistoscope-0.0.1.dist-info/LICENSE.txt
schistoscope-0.0.1.dist-info/METADATA
schistoscope-0.0.1.dist-info/WHEEL
schistoscope-0.0.1.dist-info/top_level.txt
schistoscope-0.0.1.dist-info/RECORD
