Metadata-Version: 2.1
Name: schistoscope
Version: 0.0.1
Summary: Schistoscope RPi software package
Home-page: https://github.com/Jerzeek/schistoscope
Author: Samuel Kernan Freire
Author-email: skernanfreire@gmail.com
License: UNKNOWN
Platform: UNKNOWN
Classifier: Programming Language :: Python :: 3
Classifier: License :: OSI Approved :: MIT License
Classifier: Operating System :: OS Independent
